stinger/__init__.py
stinger/cli.py
stinger/adapters/__init__.py
stinger/adapters/openai_adapter.py
stinger/api/__init__.py
stinger/api/__main__.py
stinger/api/app.py
stinger/api/models.py
stinger/api/endpoints/__init__.py
stinger/api/endpoints/check.py
stinger/api/endpoints/health.py
stinger/api/endpoints/rules.py
stinger/cli/__init__.py
stinger/cli/first_run.py
stinger/cli/main.py
stinger/cli/setup_wizard.py
stinger/core/__init__.py
stinger/core/api_key_manager.py
stinger/core/audit.py
stinger/core/config.py
stinger/core/config_validator.py
stinger/core/conversation.py
stinger/core/error_handling.py
stinger/core/guardrail_factory.py
stinger/core/guardrail_interface.py
stinger/core/health_monitor.py
stinger/core/input_validation.py
stinger/core/model_config.py
stinger/core/pipeline.py
stinger/core/preset_configs.py
stinger/core/rate_limiter.py
stinger/core/regex_security.py
stinger/core/configs/__init__.py
stinger/core/configs/global_rate_limiting.yaml
stinger/core/configs/models.yaml
stinger/data/__init__.py
stinger/data/keyword_lists/__init__.py
stinger/data/keyword_lists/harassment.txt
stinger/data/keyword_lists/medical_terms.txt
stinger/data/keyword_lists/pii.txt
stinger/data/keyword_lists/profanity.txt
stinger/data/keyword_lists/spam_indicators.txt
stinger/data/keyword_lists/toxic_language.txt
stinger/guardrails/__init__.py
stinger/guardrails/ai_code_generation_guardrail.py
stinger/guardrails/ai_pii_detection_guardrail.py
stinger/guardrails/ai_toxicity_detection_guardrail.py
stinger/guardrails/base_ai_guardrail.py
stinger/guardrails/content_moderation_guardrail.py
stinger/guardrails/keyword_block.py
stinger/guardrails/keyword_list.py
stinger/guardrails/length_guardrail.py
stinger/guardrails/pass_through.py
stinger/guardrails/prompt_injection_guardrail.py
stinger/guardrails/regex_guardrail.py
stinger/guardrails/simple_code_generation_guardrail.py
stinger/guardrails/simple_pii_detection_guardrail.py
stinger/guardrails/simple_toxicity_detection_guardrail.py
stinger_guardrails_alpha-0.1.0a5.dist-info/LICENSE
stinger_guardrails_alpha-0.1.0a5.dist-info/METADATA
stinger_guardrails_alpha-0.1.0a5.dist-info/WHEEL
stinger_guardrails_alpha-0.1.0a5.dist-info/entry_points.txt
stinger_guardrails_alpha-0.1.0a5.dist-info/top_level.txt
stinger_guardrails_alpha-0.1.0a5.dist-info/RECORD
