Metadata-Version: 2.1
Name: stinger-guardrails-alpha
Version: 0.1.0a5
Summary: AI Guardrails Framework - Comprehensive LLM safety toolkit (Alpha)
Author-email: Steve <steve@example.com>
Maintainer-email: Steve <steve@example.com>
License: MIT
Project-URL: Homepage, https://github.com/virtualsteve-star/stinger
Project-URL: Documentation, https://github.com/virtualsteve-star/stinger#readme
Project-URL: Repository, https://github.com/virtualsteve-star/stinger
Project-URL: Issues, https://github.com/virtualsteve-star/stinger/issues
Keywords: ai,llm,guardrails,safety,security,content-moderation,prompt-injection,pii-detection
Classifier: Development Status :: 3 - Alpha
Classifier: Intended Audience :: Developers
Classifier: License :: OSI Approved :: MIT License
Classifier: Operating System :: OS Independent
Classifier: Programming Language :: Python :: 3
Classifier: Programming Language :: Python :: 3.8
Classifier: Programming Language :: Python :: 3.9
Classifier: Programming Language :: Python :: 3.10
Classifier: Programming Language :: Python :: 3.11
Classifier: Programming Language :: Python :: 3.12
Classifier: Topic :: Software Development :: Libraries :: Python Modules
Classifier: Topic :: Scientific/Engineering :: Artificial Intelligence
Classifier: Topic :: Security
Requires-Python: >=3.8
License-File: LICENSE
Requires-Dist: pyyaml>=6.0
Requires-Dist: jsonschema>=4.0
Requires-Dist: cryptography>=41.0.0
Provides-Extra: ai
Requires-Dist: openai>=1.0.0; extra == "ai"
Provides-Extra: all
Requires-Dist: stinger-guardrails-alpha[ai]; extra == "all"
Requires-Dist: stinger-guardrails-alpha[api]; extra == "all"
Requires-Dist: stinger-guardrails-alpha[web-demo]; extra == "all"
Provides-Extra: api
Requires-Dist: fastapi>=0.100.0; extra == "api"
Requires-Dist: uvicorn[standard]>=0.23.0; extra == "api"
Provides-Extra: dev
Requires-Dist: pytest>=7.0; extra == "dev"
Requires-Dist: pytest-asyncio>=0.21.0; extra == "dev"
Requires-Dist: pytest-cov>=4.0; extra == "dev"
Requires-Dist: black>=23.0; extra == "dev"
Requires-Dist: isort>=5.0; extra == "dev"
Requires-Dist: mypy>=1.0; extra == "dev"
Requires-Dist: twine>=4.0; extra == "dev"
Requires-Dist: build>=0.10; extra == "dev"
Provides-Extra: web-demo
Requires-Dist: fastapi>=0.100.0; extra == "web-demo"
Requires-Dist: uvicorn>=0.23.0; extra == "web-demo"
Requires-Dist: python-multipart>=0.0.6; extra == "web-demo"
Requires-Dist: watchdog>=3.0.0; extra == "web-demo"
